LICENSE
README.md
setup.py
aiotor/__init__.py
aiotor/controller.py
aiotor/events.py
aiotor/onions.py
aiotor/textprotocol.py
python_aiotor.egg-info/PKG-INFO
python_aiotor.egg-info/SOURCES.txt
python_aiotor.egg-info/dependency_links.txt
python_aiotor.egg-info/requires.txt
python_aiotor.egg-info/top_level.txt