Metadata-Version: 2.1
Name: python-aiotor
Version: 0.1.0
Summary: asyncio Tor controller client
Home-page: https://github.com/wybiral/aiotor
Author: Davy Wybiral
Author-email: davy.wybiral@gmail.com
License: MIT
Platform: UNKNOWN
Classifier: Programming Language :: Python :: 3
Classifier: License :: OSI Approved :: MIT License
Classifier: Operating System :: OS Independent
License-File: LICENSE
